janito/README.md
janito/__init__.py
janito/__main__.py
janito/_version.py
janito/agent_events.py
janito/config.py
janito/config_manager.py
janito/conversation_history.py
janito/dir_walk_utils.py
janito/driver_events.py
janito/exceptions.py
janito/formatting.py
janito/formatting_token.py
janito/gitignore_utils.py
janito/hello.txt
janito/perf_singleton.py
janito/performance_collector.py
janito/platform_discovery.py
janito/provider_config.py
janito/provider_registry.py
janito/report_events.py
janito/shell.bak.zip
janito/utils.py
janito/agent/setup_agent.py
janito/agent/templates/profiles/system_prompt_template_Developer_with_Python_Tools.txt.j2
janito/agent/templates/profiles/system_prompt_template_developer.txt.j2
janito/agent/templates/profiles/system_prompt_template_market_analyst.txt.j2
janito/agent/templates/profiles/system_prompt_template_model_conversation_without_tools_or_context.txt.j2
janito/cli/__init__.py
janito/cli/config.py
janito/cli/console.py
janito/cli/main.py
janito/cli/main_cli.py
janito/cli/prompt_core.py
janito/cli/prompt_handler.py
janito/cli/prompt_setup.py
janito/cli/rich_terminal_reporter.py
janito/cli/utils.py
janito/cli/verbose_output.py
janito/cli/chat_mode/bindings.py
janito/cli/chat_mode/chat_entry.py
janito/cli/chat_mode/prompt_style.py
janito/cli/chat_mode/script_runner.py
janito/cli/chat_mode/session.py
janito/cli/chat_mode/toolbar.py
janito/cli/chat_mode/shell/autocomplete.py
janito/cli/chat_mode/shell/commands.bak.zip
janito/cli/chat_mode/shell/input_history.py
janito/cli/chat_mode/shell/session.bak.zip
janito/cli/chat_mode/shell/commands/__init__.py
janito/cli/chat_mode/shell/commands/_priv_check.py
janito/cli/chat_mode/shell/commands/_priv_status.py
janito/cli/chat_mode/shell/commands/bang.py
janito/cli/chat_mode/shell/commands/base.py
janito/cli/chat_mode/shell/commands/clear.py
janito/cli/chat_mode/shell/commands/clear_context.py
janito/cli/chat_mode/shell/commands/conversation_restart.py
janito-3.17.0.dist-info/licenses/LICENSE
janito-3.17.0.dist-info/METADATA
janito-3.17.0.dist-info/WHEEL
janito-3.17.0.dist-info/entry_points.txt
janito-3.17.0.dist-info/top_level.txt
janito-3.17.0.dist-info/RECORD
