Metadata-Version: 2.4
Name: janito
Version: 3.17.0
Summary: A new Python package called janito.
Author-email: João Pinto <janito@ikignosis.org>
Project-URL: Homepage, https://github.com/ikignosis/janito
Requires-Python: >=3.8
License-File: LICENSE
Requires-Dist: attrs==25.3.0
Requires-Dist: rich==14.0.0
Requires-Dist: pathspec==0.12.1
Requires-Dist: setuptools>=61.0
Requires-Dist: pyyaml>=6.0
Requires-Dist: jinja2>=3.0.0
Requires-Dist: prompt_toolkit>=3.0.51
Requires-Dist: lxml>=5.4.0
Requires-Dist: requests>=2.32.4
Requires-Dist: bs4>=0.0.2
Requires-Dist: questionary>=2.0.1
Requires-Dist: openai>=1.68.0
Requires-Dist: Pillow>=10.0.0
Provides-Extra: dev
Requires-Dist: pytest; extra == "dev"
Requires-Dist: pre-commit; extra == "dev"
Requires-Dist: ruff==0.11.9; extra == "dev"
Requires-Dist: detect-secrets==1.4.0; extra == "dev"
Requires-Dist: codespell==2.4.1; extra == "dev"
Requires-Dist: black; extra == "dev"
Requires-Dist: questionary>=2.0.1; extra == "dev"
Requires-Dist: setuptools_scm>=8.0; extra == "dev"
Requires-Dist: mkdocs; extra == "dev"
Requires-Dist: mkdocs-material; extra == "dev"
Requires-Dist: mkdocs-material-extensions; extra == "dev"
Dynamic: license-file
